{
  "miniprogramRoot": "dist/",
  "projectname": "mall-wechat-mp",
  "description": "电商微信小程序",
  "appid": "wx12756a2557e97544",
  "setting": {
    "urlCheck": false,
    "es6": false,
    "enhance": false,
    "compileHotReLoad": false,
    "postcss": false,
    "minified": true,
    "ignoreUploadUnusedFiles": true,
    "babelSetting": {
      "ignore": [],
      "disablePlugins": [],
      "outputPath": ""
    }
  },
  "compileType": "miniprogram",
  "libVersion": "3.2.0",
  "srcMiniprogramRoot": "dist/",
  "packOptions": {
    "ignore": [],
    "include": []
  },
  "condition": {},
  "editorSetting": {
    "tabIndent": "insertSpaces",
    "tabSize": 2
  }
}